[
  {
    "pk": 1,
    "model": "patients.patient",
    "fields": {
      "weight": "97",
      "blood_group": "b-positive",
      "gender": "male",
      "height": "159",
      "date_of_birth": "1990-04-07",
      "user": 1,
      "employer": 1
    }
  },
  {
    "pk": 2,
    "model": "patients.patient",
    "fields": {
      "weight": null,
      "blood_group": null,
      "gender": null,
      "height": null,
      "date_of_birth": null,
      "user": 2,
      "employer": null
    }
  },
  {
    "pk": 3,
    "model": "patients.patient",
    "fields": {
      "weight": null,
      "blood_group": null,
      "gender": null,
      "height": null,
      "date_of_birth": null,
      "user": 3,
      "employer": null
    }
  },
  {
    "pk": 1,
    "model": "patients.relationshiptype",
    "fields": {
      "preffered": false,
      "dependent": true,
      "a_is_to_b": "Husband",
      "b_is_to_a": "Wife"
    }
  },
  {
    "pk": 2,
    "model": "patients.relationshiptype",
    "fields": {
      "preffered": false,
      "dependent": true,
      "a_is_to_b": "Wife",
      "b_is_to_a": "Husband"
    }
  },
  {
    "pk": 3,
    "model": "patients.relationshiptype",
    "fields": {
      "preffered": false,
      "dependent": true,
      "a_is_to_b": "Child",
      "b_is_to_a": "Parent"
    }
  },
  {
    "pk": 4,
    "model": "patients.relationshiptype",
    "fields": {
      "preffered": false,
      "dependent": true,
      "a_is_to_b": "Child",
      "b_is_to_a": "Guardian"
    }
  },
  {
    "pk": 1,
    "model": "patients.relationship",
    "fields": {
      "next_of_kin": true,
      "person_b": 3,
      "relationship": 2,
      "person_a": 2
    }
  }
]